[
               {
                     "name":"Auto Watche",
                     "price": "£290.00",
                     "img":"http://sigmadigitalpartners.com/themes/templatemonster/wp/smatch/wp-content/uploads/2020/11/watch-2-1-295x300.jpg",
                     "about":"",
                     "offer": "-12%",
                     "like": "123"
               },
               {
                              "name":"Diving Watch",
                              "price": "£350.00 – £400.00",
                              "img":"http://sigmadigitalpartners.com/themes/templatemonster/wp/smatch/wp-content/uploads/2020/11/watch-6-1-450x458.jpg",
                              "about":"",
                              "offer": "-18.6%",
                              "like": "230"
                        },
                        {
                              "name":"Mechanical Watches",
                              "price": "£220.00",
                              "img":"http://sigmadigitalpartners.com/themes/templatemonster/wp/smatch/wp-content/uploads/2020/11/watch-3-1-295x300.jpg",
                              "about":"",
                              "offer": "10%",
                              "like": "110"
                        },
                        {
                              "name":"Sports Watch",
                              "price": "£300.00 -£290.00",
                              "img":"http://sigmadigitalpartners.com/themes/templatemonster/wp/smatch/wp-content/uploads/2020/11/watch-5-1-450x458.jpg",
                              "about":"",
                              "offer": "-3%",
                              "like": "156"
                        },
                        {
                              "name":"Swiss Watch",
                              "price": "£285.00",
                              "img":"http://sigmadigitalpartners.com/themes/templatemonster/wp/smatch/wp-content/uploads/2020/11/watch-1-1-295x300.jpg",
                              "about":"",
                              "offer": "14.5%",
                              "like": "117"
                        },
                        {
                              "name":"Trench Watch",
                              "price": "£280.00",
                              "img":"http://sigmadigitalpartners.com/themes/templatemonster/wp/smatch/wp-content/uploads/2020/11/watch-4-1-295x300.jpg",
                              "about":"",
                              "offer": "20%",
                              "like": "76"
                        },
                        {
                              "name":"",
                              "price": "",
                              "about":"",
                              "offer": "",
                              "like": ""
                        }
]